rmm/__init__.py
rmm/__main__.py
rmm/cli.py
rmm/config.py
rmm/exception.py
rmm/manager.py
rmm/mod.py
rmm/modlist.py
rmm/modsconfig.py
rmm/multiselect.py
rmm/path.py
rmm/steam.py
rmm/util.py
rmm_spoons-1.1.2.dist-info/LICENSE
rmm_spoons-1.1.2.dist-info/METADATA
rmm_spoons-1.1.2.dist-info/WHEEL
rmm_spoons-1.1.2.dist-info/entry_points.txt
rmm_spoons-1.1.2.dist-info/RECORD
