Metadata-Version: 2.1
Name: rmm-spoons
Version: 1.1.2
Summary: A RimWorld Mod Manager
Home-page: https://github.com/spoons/rmm
License: GPLv3
Author: Michael Ciociola
Author-email: michael@ciocio.la
Requires-Python: >3.8,<4.0
Classifier: License :: OSI Approved :: GNU Affero General Public License v3
Classifier: License :: Other/Proprietary License
Classifier: Operating System :: OS Independent
Classifier: Programming Language :: Python :: 3
Classifier: Programming Language :: Python :: 3.9
Classifier: Programming Language :: Python :: 3.10
Classifier: Programming Language :: Python :: 3.11
Classifier: Topic :: Games/Entertainment
Classifier: Topic :: System :: Archiving :: Packaging
Requires-Dist: beautifulsoup4 (>=4.12.2,<5.0.0)
Requires-Dist: networkx (>=3.1,<4.0)
Requires-Dist: tabulate (>=0.9.0,<0.10.0)
Project-URL: Repository, https://github.com/spoons/rmm
